monasca_log_api/__init__.py
monasca_log_api/config.py
monasca_log_api/version.py
monasca_log_api/app/__init__.py
monasca_log_api/app/api.py
monasca_log_api/app/main.py
monasca_log_api/app/wsgi.py
monasca_log_api/app/base/__init__.py
monasca_log_api/app/base/error_handlers.py
monasca_log_api/app/base/exceptions.py
monasca_log_api/app/base/log_publisher.py
monasca_log_api/app/base/model.py
monasca_log_api/app/base/request.py
monasca_log_api/app/base/request_context.py
monasca_log_api/app/base/validation.py
monasca_log_api/app/controller/__init__.py
monasca_log_api/app/controller/healthchecks.py
monasca_log_api/app/controller/versions.py
monasca_log_api/app/controller/api/__init__.py
monasca_log_api/app/controller/api/headers.py
monasca_log_api/app/controller/api/healthcheck_api.py
monasca_log_api/app/controller/api/logs_api.py
monasca_log_api/app/controller/api/versions_api.py
monasca_log_api/app/controller/v2/__init__.py
monasca_log_api/app/controller/v2/logs.py
monasca_log_api/app/controller/v2/aid/__init__.py
monasca_log_api/app/controller/v2/aid/service.py
monasca_log_api/app/controller/v3/__init__.py
monasca_log_api/app/controller/v3/logs.py
monasca_log_api/app/controller/v3/aid/__init__.py
monasca_log_api/app/controller/v3/aid/bulk_processor.py
monasca_log_api/app/controller/v3/aid/helpers.py
monasca_log_api/conf/__init__.py
monasca_log_api/conf/healthcheck.py
monasca_log_api/conf/log_publisher.py
monasca_log_api/conf/monitoring.py
monasca_log_api/conf/role_middleware.py
monasca_log_api/conf/service.py
monasca_log_api/db/__init__.py
monasca_log_api/db/common/__init__.py
monasca_log_api/db/common/model.py
monasca_log_api/db/repo/__init__.py
monasca_log_api/db/repo/logs_repository.py
monasca_log_api/healthcheck/__init__.py
monasca_log_api/healthcheck/kafka_check.py
monasca_log_api/middleware/__init__.py
monasca_log_api/middleware/role_middleware.py
monasca_log_api/monitoring/__init__.py
monasca_log_api-2.11.0.dist-info/DESCRIPTION.rst
monasca_log_api-2.11.0.dist-info/METADATA
monasca_log_api-2.11.0.dist-info/RECORD
monasca_log_api-2.11.0.dist-info/WHEEL
monasca_log_api-2.11.0.dist-info/entry_points.txt
monasca_log_api-2.11.0.dist-info/metadata.json
monasca_log_api-2.11.0.dist-info/pbr.json
monasca_log_api-2.11.0.dist-info/top_level.txt
