Metadata-Version: 2.0
Name: monasca-log-api
Version: 2.11.0
Summary: Monasca API for sending log entries
Home-page: https://github.com/openstack/monasca-log-api
Author: OpenStack
Author-email: openstack-discuss@lists.openstack.org
License: UNKNOWN
Platform: UNKNOWN
Classifier: Environment :: OpenStack
Classifier: Intended Audience :: Information Technology
Classifier: Intended Audience :: System Administrators
Classifier: License :: OSI Approved :: Apache Software License
Classifier: Operating System :: POSIX :: Linux
Classifier: Programming Language :: Python
Classifier: Programming Language :: Python :: 2
Classifier: Programming Language :: Python :: 2.7
Classifier: Programming Language :: Python :: 3
Classifier: Programming Language :: Python :: 3.6
Classifier: Programming Language :: Python :: 3.7
Requires-Dist: Paste (>=2.0.2)
Requires-Dist: PasteDeploy (>=1.5.0)
Requires-Dist: eventlet (!=0.18.3,!=0.20.1,!=0.21.0,>=0.18.2)
Requires-Dist: falcon (>=2.0.0)
Requires-Dist: keystonemiddleware (>=4.17.0)
Requires-Dist: monasca-common (>=2.7.0)
Requires-Dist: monasca-statsd (>=1.1.0)
Requires-Dist: oslo.config (>=5.2.0)
Requires-Dist: oslo.context (>=2.19.2)
Requires-Dist: oslo.log (>=3.36.0)
Requires-Dist: oslo.middleware (>=3.31.0)
Requires-Dist: oslo.serialization (!=2.19.1,>=2.18.0)
Requires-Dist: oslo.utils (>=3.33.0)
Requires-Dist: pbr (!=2.1.0,>=2.0.0)
